fullcalendar_component/__init__.py
fullcalendar_component/frontend/build/asset-manifest.json
fullcalendar_component/frontend/build/bootstrap.min.css
fullcalendar_component/frontend/build/index.html
fullcalendar_component/frontend/build/static/js/2.5fd6143f.chunk.js
fullcalendar_component/frontend/build/static/js/2.5fd6143f.chunk.js.LICENSE.txt
fullcalendar_component/frontend/build/static/js/2.5fd6143f.chunk.js.map
fullcalendar_component/frontend/build/static/js/main.3ec89947.chunk.js
fullcalendar_component/frontend/build/static/js/main.3ec89947.chunk.js.map
fullcalendar_component/frontend/build/static/js/runtime-main.ccbf7c91.js
fullcalendar_component/frontend/build/static/js/runtime-main.ccbf7c91.js.map
Streamlit_Fullcalendar_Component-0.0.1.dist-info/LICENSE
Streamlit_Fullcalendar_Component-0.0.1.dist-info/METADATA
Streamlit_Fullcalendar_Component-0.0.1.dist-info/WHEEL
Streamlit_Fullcalendar_Component-0.0.1.dist-info/top_level.txt
Streamlit_Fullcalendar_Component-0.0.1.dist-info/RECORD
