Metadata-Version: 2.1
Name: Streamlit-Fullcalendar-Component
Version: 0.0.1
Summary: Fullcalendar Support for Streamlit
Home-page: https://github.com/JettChenT/streamlit-fullcalendar
Author: Jett Chen
Author-email: me@jettchen.me
Requires-Python: >=3.6
License-File: LICENSE
Requires-Dist: streamlit (>=0.63)
